{"kind":"youtube#playlistItemListResponse","etag":"o-iNy6KIuEUV5b3XgTb3J1DsYmE","nextPageToken":"EAAaBlBUOkNESQ","items":[{"kind":"youtube#playlistItem","etag":"BfZPbS3cpde2Yy3Hd-Q6yhfrkHI","id":"UExGUlAyX3JmWmNnRFl5OVBYVmdLcnhkRmhFVzRPbllYYS41NkI0NEY2RDEwNTU3Q0M2","snippet":{"publishedAt":"2016-08-08T11:40:11Z","channelId":"UCZ2I0UZvP3cEcbgESWxkHmA","title":"BB VS ヒカキン ボイパ対決 Bad Apple!!","description":"ニコから。720P高画質　http:\/\/www.nicovideo.jp\/watch\/sm25932048","thumbnails":{"default":{"url":"https:\/\/i.ytimg.com\/vi\/4azw7OwWl_k\/default.jpg","width":120,"height":90},"medium":{"url":"https:\/\/i.ytimg.com\/vi\/4azw7OwWl_k\/mqdefault.jpg","width":320,"height":180},"high":{"url":"https:\/\/i.ytimg.com\/vi\/4azw7OwWl_k\/hqdefault.jpg","width":480,"height":360},"standard":{"url":"https:\/\/i.ytimg.com\/vi\/4azw7OwWl_k\/sddefault.jpg","width":640,"height":480},"maxres":{"url":"https:\/\/i.ytimg.com\/vi\/4azw7OwWl_k\/maxresdefault.jpg","width":1280,"height":720}},"channelTitle":"최환","playlistId":"PLFRP2_rfZcgDYy9PXVgKrxdFhEW4OnYXa","position":0,"resourceId":{"kind":"youtube#video","videoId":"4azw7OwWl_k"},"videoOwnerChannelTitle":"Syamu Love","videoOwnerChannelId":"UCUjftzItaDhGbDEU5yCVnPQ"}},{"kind":"youtube#playlistItem","etag":"lE8azc4kJVKtLIHr4MUJRQV0h3k","id":"UExGUlAyX3JmWmNnRFl5OVBYVmdLcnhkRmhFVzRPbllYYS4yODlGNEE0NkRGMEEzMEQy","snippet":{"publishedAt":"2016-08-08T11:40:35Z","channelId":"UCZ2I0UZvP3cEcbgESWxkHmA","title":"【転載】BB VS sm666 EX ボイパ対決 Bad Apple!!","description":"","thumbnails":{"default":{"url":"https:\/\/i.ytimg.com\/vi\/6vsX2NbE98s\/default.jpg","width":120,"height":90},"medium":{"url":"https:\/\/i.ytimg.com\/vi\/6vsX2NbE98s\/mqdefault.jpg","width":320,"height":180},"high":{"url":"https:\/\/i.ytimg.com\/vi\/6vsX2NbE98s\/hqdefault.jpg","width":480,"height":360},"standard":{"url":"https:\/\/i.ytimg.com\/vi\/6vsX2NbE98s\/sddefault.jpg","width":640,"height":480}},"channelTitle":"최환","playlistId":"PLFRP2_rfZcgDYy9PXVgKrxdFhEW4OnYXa","position":1,"resourceId":{"kind":"youtube#video","videoId":"6vsX2NbE98s"},"videoOwnerChannelTitle":"ぽうかいむら","videoOwnerChannelId":"UCx9EEAdyiN5riC2Q7ptqrpg"}},{"kind":"youtube#playlistItem","etag":"lnzG-7RVZWlHIRMC2j0dw71GDYY","id":"UExGUlAyX3JmWmNnRFl5OVBYVmdLcnhkRmhFVzRPbllYYS41MjE1MkI0OTQ2QzJGNzNG","snippet":{"publishedAt":"2016-08-08T11:40:51Z","channelId":"UCZ2I0UZvP3cEcbgESWxkHmA","title":"BB vs SYNTHKIN ボイパ対決 Bad Apple!!","description":"Sound Material by GTX999: https:\/\/www.youtube.com\/watch?v=shs9Cqp_cVk","thumbnails":{"default":{"url":"https:\/\/i.ytimg.com\/vi\/J_fgqoyuUQo\/default.jpg","width":120,"height":90},"medium":{"url":"https:\/\/i.ytimg.com\/vi\/J_fgqoyuUQo\/mqdefault.jpg","width":320,"height":180},"high":{"url":"https:\/\/i.ytimg.com\/vi\/J_fgqoyuUQo\/hqdefault.jpg","width":480,"height":360},"standard":{"url":"https:\/\/i.ytimg.com\/vi\/J_fgqoyuUQo\/sddefault.jpg","width":640,"height":480},"maxres":{"url":"https:\/\/i.ytimg.com\/vi\/J_fgqoyuUQo\/maxresdefault.jpg","width":1280,"height":720}},"channelTitle":"최환","playlistId":"PLFRP2_rfZcgDYy9PXVgKrxdFhEW4OnYXa","position":2,"resourceId":{"kind":"youtube#video","videoId":"J_fgqoyuUQo"},"videoOwnerChannelTitle":"ＤＡＭＯ.","videoOwnerChannelId":"UC4Fd73MocrFcljE0IzfMVXg"}},{"kind":"youtube#playlistItem","etag":"BBW2GWo4gzL4xsgSrIaiV4ApwlM","id":"UExGUlAyX3JmWmNnRFl5OVBYVmdLcnhkRmhFVzRPbllYYS4wOTA3OTZBNzVEMTUzOTMy","snippet":{"publishedAt":"2016-08-08T11:40:56Z","channelId":"UCZ2I0UZvP3cEcbgESWxkHmA","title":"Private video","description":"This video is private.","thumbnails":{},"channelTitle":"최환","playlistId":"PLFRP2_rfZcgDYy9PXVgKrxdFhEW4OnYXa","position":3,"resourceId":{"kind":"youtube#video","videoId":"qOGRGkR1Nr0"}}},{"kind":"youtube#playlistItem","etag":"V0_Z4DbLddmKdctPzeqm-6lHIUU","id":"UExGUlAyX3JmWmNnRFl5OVBYVmdLcnhkRmhFVzRPbllYYS5DQUNERDQ2NkIzRUQxNTY1","snippet":{"publishedAt":"2016-08-08T11:41:47Z","channelId":"UCZ2I0UZvP3cEcbgESWxkHmA","title":"BlueBack vs AnotherHIKAKIN Voice Percussion Battle BadApple!!","description":"","thumbnails":{"default":{"url":"https:\/\/i.ytimg.com\/vi\/zM4b67G5yGo\/default.jpg","width":120,"height":90},"medium":{"url":"https:\/\/i.ytimg.com\/vi\/zM4b67G5yGo\/mqdefault.jpg","width":320,"height":180},"high":{"url":"https:\/\/i.ytimg.com\/vi\/zM4b67G5yGo\/hqdefault.jpg","width":480,"height":360},"standard":{"url":"https:\/\/i.ytimg.com\/vi\/zM4b67G5yGo\/sddefault.jpg","width":640,"height":480},"maxres":{"url":"https:\/\/i.ytimg.com\/vi\/zM4b67G5yGo\/maxresdefault.jpg","width":1280,"height":720}},"channelTitle":"최환","playlistId":"PLFRP2_rfZcgDYy9PXVgKrxdFhEW4OnYXa","position":4,"resourceId":{"kind":"youtube#video","videoId":"zM4b67G5yGo"},"videoOwnerChannelTitle":"CH STEVE","videoOwnerChannelId":"UCbxq9dxzxSmxtj9F4BW5bAg"}},{"kind":"youtube#playlistItem","etag":"dtBVY8XQi5Ftf-YiZEqXOuJQVp8","id":"UExGUlAyX3JmWmNnRFl5OVBYVmdLcnhkRmhFVzRPbllYYS40NzZCMERDMjVEN0RFRThB","snippet":{"publishedAt":"2016-08-08T11:42:51Z","channelId":"UCZ2I0UZvP3cEcbgESWxkHmA","title":"【素材】BB VS Overlord H ボイパ対決 Bad Apple!!","description":"リクエストはコメで","thumbnails":{"default":{"url":"https:\/\/i.ytimg.com\/vi\/ZK0rYaxhh-Q\/default.jpg","width":120,"height":90},"medium":{"url":"https:\/\/i.ytimg.com\/vi\/ZK0rYaxhh-Q\/mqdefault.jpg","width":320,"height":180},"high":{"url":"https:\/\/i.ytimg.com\/vi\/ZK0rYaxhh-Q\/hqdefault.jpg","width":480,"height":360},"standard":{"url":"https:\/\/i.ytimg.com\/vi\/ZK0rYaxhh-Q\/sddefault.jpg","width":640,"height":480}},"channelTitle":"최환","playlistId":"PLFRP2_rfZcgDYy9PXVgKrxdFhEW4OnYXa","position":5,"resourceId":{"kind":"youtube#video","videoId":"ZK0rYaxhh-Q"},"videoOwnerChannelTitle":"佐世保","videoOwnerChannelId":"UCocnqSKOHuopVyCP72bqGwA"}},{"kind":"youtube#playlistItem","etag":"YL1z7kV8Eo1TmKwZSVkGUNrHOCA","id":"UExGUlAyX3JmWmNnRFl5OVBYVmdLcnhkRmhFVzRPbllYYS4zMDg5MkQ5MEVDMEM1NTg2","snippet":{"publishedAt":"2016-08-08T11:43:16Z","channelId":"UCZ2I0UZvP3cEcbgESWxkHmA","title":"BB Vs Shinsekin ボイパ対決 grief seed  bad apple","description":"","thumbnails":{"default":{"url":"https:\/\/i.ytimg.com\/vi\/khXyatEoSw0\/default.jpg","width":120,"height":90},"medium":{"url":"https:\/\/i.ytimg.com\/vi\/khXyatEoSw0\/mqdefault.jpg","width":320,"height":180},"high":{"url":"https:\/\/i.ytimg.com\/vi\/khXyatEoSw0\/hqdefault.jpg","width":480,"height":360},"standard":{"url":"https:\/\/i.ytimg.com\/vi\/khXyatEoSw0\/sddefault.jpg","width":640,"height":480},"maxres":{"url":"https:\/\/i.ytimg.com\/vi\/khXyatEoSw0\/maxresdefault.jpg","width":1280,"height":720}},"channelTitle":"최환","playlistId":"PLFRP2_rfZcgDYy9PXVgKrxdFhEW4OnYXa","position":6,"resourceId":{"kind":"youtube#video","videoId":"khXyatEoSw0"},"videoOwnerChannelTitle":"Found YTP\/MV","videoOwnerChannelId":"UCBrSEc1W9rBqaqpyCzCei_g"}},{"kind":"youtube#playlistItem","etag":"mWX8QlpSdgtkDPd9IBNUWzSquY8","id":"UExGUlAyX3JmWmNnRFl5OVBYVmdLcnhkRmhFVzRPbllYYS41QTY1Q0UxMTVCODczNThE","snippet":{"publishedAt":"2016-08-08T11:43:26Z","channelId":"UCZ2I0UZvP3cEcbgESWxkHmA","title":"Private video","description":"This video is private.","thumbnails":{},"channelTitle":"최환","playlistId":"PLFRP2_rfZcgDYy9PXVgKrxdFhEW4OnYXa","position":7,"resourceId":{"kind":"youtube#video","videoId":"Vt2hI-LnpD0"}}},{"kind":"youtube#playlistItem","etag":"RtKugmfNGd-XZqDHGiPiL8MaKTg","id":"UExGUlAyX3JmWmNnRFl5OVBYVmdLcnhkRmhFVzRPbllYYS4yMUQyQTQzMjRDNzMyQTMy","snippet":{"publishedAt":"2016-08-08T11:43:37Z","channelId":"UCZ2I0UZvP3cEcbgESWxkHmA","title":"BB vs HIKAKIN FAMILY ボイパ対決 Bad Apple!!","description":"","thumbnails":{"default":{"url":"https:\/\/i.ytimg.com\/vi\/UzdUTV0qVO8\/default.jpg","width":120,"height":90},"medium":{"url":"https:\/\/i.ytimg.com\/vi\/UzdUTV0qVO8\/mqdefault.jpg","width":320,"height":180},"high":{"url":"https:\/\/i.ytimg.com\/vi\/UzdUTV0qVO8\/hqdefault.jpg","width":480,"height":360},"standard":{"url":"https:\/\/i.ytimg.com\/vi\/UzdUTV0qVO8\/sddefault.jpg","width":640,"height":480},"maxres":{"url":"https:\/\/i.ytimg.com\/vi\/UzdUTV0qVO8\/maxresdefault.jpg","width":1280,"height":720}},"channelTitle":"최환","playlistId":"PLFRP2_rfZcgDYy9PXVgKrxdFhEW4OnYXa","position":8,"resourceId":{"kind":"youtube#video","videoId":"UzdUTV0qVO8"},"videoOwnerChannelTitle":"ＤＡＭＯ.","videoOwnerChannelId":"UC4Fd73MocrFcljE0IzfMVXg"}},{"kind":"youtube#playlistItem","etag":"5W5wxYENs98musD4gvm8uE_evnA","id":"UExGUlAyX3JmWmNnRFl5OVBYVmdLcnhkRmhFVzRPbllYYS5DQ0MyQ0Y4Mzg0M0VGOEYw","snippet":{"publishedAt":"2016-08-08T11:44:05Z","channelId":"UCZ2I0UZvP3cEcbgESWxkHmA","title":"BadApple Scan BB Custom","description":"AnotherHIKAKIN入れた","thumbnails":{"default":{"url":"https:\/\/i.ytimg.com\/vi\/QpTReBxj_To\/default.jpg","width":120,"height":90},"medium":{"url":"https:\/\/i.ytimg.com\/vi\/QpTReBxj_To\/mqdefault.jpg","width":320,"height":180},"high":{"url":"https:\/\/i.ytimg.com\/vi\/QpTReBxj_To\/hqdefault.jpg","width":480,"height":360},"standard":{"url":"https:\/\/i.ytimg.com\/vi\/QpTReBxj_To\/sddefault.jpg","width":640,"height":480},"maxres":{"url":"https:\/\/i.ytimg.com\/vi\/QpTReBxj_To\/maxresdefault.jpg","width":1280,"height":720}},"channelTitle":"최환","playlistId":"PLFRP2_rfZcgDYy9PXVgKrxdFhEW4OnYXa","position":9,"resourceId":{"kind":"youtube#video","videoId":"QpTReBxj_To"},"videoOwnerChannelTitle":"CH STEVE","videoOwnerChannelId":"UCbxq9dxzxSmxtj9F4BW5bAg"}},{"kind":"youtube#playlistItem","etag":"-Mb6uwXyl3HsRby5zDrRjIsW0bM","id":"UExGUlAyX3JmWmNnRFl5OVBYVmdLcnhkRmhFVzRPbllYYS4yQUE2Q0JEMTk4NTM3RTZC","snippet":{"publishedAt":"2016-08-08T11:44:08Z","channelId":"UCZ2I0UZvP3cEcbgESWxkHmA","title":"Another Hikakin Vs BBボイパ対決 Bad apple","description":"","thumbnails":{"default":{"url":"https:\/\/i.ytimg.com\/vi\/DMJ34tD3sRw\/default.jpg","width":120,"height":90},"medium":{"url":"https:\/\/i.ytimg.com\/vi\/DMJ34tD3sRw\/mqdefault.jpg","width":320,"height":180},"high":{"url":"https:\/\/i.ytimg.com\/vi\/DMJ34tD3sRw\/hqdefault.jpg","width":480,"height":360},"standard":{"url":"https:\/\/i.ytimg.com\/vi\/DMJ34tD3sRw\/sddefault.jpg","width":640,"height":480},"maxres":{"url":"https:\/\/i.ytimg.com\/vi\/DMJ34tD3sRw\/maxresdefault.jpg","width":1280,"height":720}},"channelTitle":"최환","playlistId":"PLFRP2_rfZcgDYy9PXVgKrxdFhEW4OnYXa","position":10,"resourceId":{"kind":"youtube#video","videoId":"DMJ34tD3sRw"},"videoOwnerChannelTitle":"Found YTP\/MV","videoOwnerChannelId":"UCBrSEc1W9rBqaqpyCzCei_g"}},{"kind":"youtube#playlistItem","etag":"5XlEuS6vXpiQSgO-kwtP8Wkm6UE","id":"UExGUlAyX3JmWmNnRFl5OVBYVmdLcnhkRmhFVzRPbllYYS5CMEQ2Mjk5NTc3NDZFRUNB","snippet":{"publishedAt":"2016-08-08T11:44:53Z","channelId":"UCZ2I0UZvP3cEcbgESWxkHmA","title":"Deleted video","description":"This video is unavailable.","thumbnails":{},"channelTitle":"최환","playlistId":"PLFRP2_rfZcgDYy9PXVgKrxdFhEW4OnYXa","position":11,"resourceId":{"kind":"youtube#video","videoId":"AS32l6-AMhw"}}},{"kind":"youtube#playlistItem","etag":"1-qA1zhXBTS0YdZfx0y8wi8bMec","id":"UExGUlAyX3JmWmNnRFl5OVBYVmdLcnhkRmhFVzRPbllYYS45RjNFMDhGQ0Q2RkFCQTc1","snippet":{"publishedAt":"2016-08-08T12:09:46Z","channelId":"UCZ2I0UZvP3cEcbgESWxkHmA","title":"BB vs HIKAKIN ボイパ対決 Grief Seed!!","description":"PV Graphics: https:\/\/www.youtube.com\/watch?v=N_Z8-HVXGGo\nBGM: https:\/\/www.youtube.com\/watch?v=cSDdSjwbYKU\n\nThis took a lot longer to make than i thought it would","thumbnails":{"default":{"url":"https:\/\/i.ytimg.com\/vi\/YMn_7eXSC28\/default.jpg","width":120,"height":90},"medium":{"url":"https:\/\/i.ytimg.com\/vi\/YMn_7eXSC28\/mqdefault.jpg","width":320,"height":180},"high":{"url":"https:\/\/i.ytimg.com\/vi\/YMn_7eXSC28\/hqdefault.jpg","width":480,"height":360},"standard":{"url":"https:\/\/i.ytimg.com\/vi\/YMn_7eXSC28\/sddefault.jpg","width":640,"height":480},"maxres":{"url":"https:\/\/i.ytimg.com\/vi\/YMn_7eXSC28\/maxresdefault.jpg","width":1280,"height":720}},"channelTitle":"최환","playlistId":"PLFRP2_rfZcgDYy9PXVgKrxdFhEW4OnYXa","position":12,"resourceId":{"kind":"youtube#video","videoId":"YMn_7eXSC28"},"videoOwnerChannelTitle":"ＤＡＭＯ.","videoOwnerChannelId":"UC4Fd73MocrFcljE0IzfMVXg"}},{"kind":"youtube#playlistItem","etag":"czBTO3Cu8xrh2EMZw48T3qd5A9Y","id":"UExGUlAyX3JmWmNnRFl5OVBYVmdLcnhkRmhFVzRPbllYYS5BRjJDODk5REM0NjkzMUIy","snippet":{"publishedAt":"2016-08-08T12:09:52Z","channelId":"UCZ2I0UZvP3cEcbgESWxkHmA","title":"BB vs HIKAKIN ボイパ対決 NO BGM","description":"Voice only version so you can use whatever BGM you'd like. Sorry if there's any minor desync...","thumbnails":{"default":{"url":"https:\/\/i.ytimg.com\/vi\/cPqEQGSrvqA\/default.jpg","width":120,"height":90},"medium":{"url":"https:\/\/i.ytimg.com\/vi\/cPqEQGSrvqA\/mqdefault.jpg","width":320,"height":180},"high":{"url":"https:\/\/i.ytimg.com\/vi\/cPqEQGSrvqA\/hqdefault.jpg","width":480,"height":360},"standard":{"url":"https:\/\/i.ytimg.com\/vi\/cPqEQGSrvqA\/sddefault.jpg","width":640,"height":480},"maxres":{"url":"https:\/\/i.ytimg.com\/vi\/cPqEQGSrvqA\/maxresdefault.jpg","width":1280,"height":720}},"channelTitle":"최환","playlistId":"PLFRP2_rfZcgDYy9PXVgKrxdFhEW4OnYXa","position":13,"resourceId":{"kind":"youtube#video","videoId":"cPqEQGSrvqA"},"videoOwnerChannelTitle":"ＤＡＭＯ.","videoOwnerChannelId":"UC4Fd73MocrFcljE0IzfMVXg"}},{"kind":"youtube#playlistItem","etag":"c9IU8A8cPPamhSSgNW0NsMKKW9M","id":"UExGUlAyX3JmWmNnRFl5OVBYVmdLcnhkRmhFVzRPbllYYS4zQzFBN0RGNzNFREFCMjBE","snippet":{"publishedAt":"2016-08-08T12:10:33Z","channelId":"UCZ2I0UZvP3cEcbgESWxkHmA","title":"(転載)GB VS メタキン　ボイパ対決 Bad Apple!!","description":"from Baidu百度\nBaidu百度からはDL出来ないのでBiliBiliに転載されたのを5KPlayerでDLしました\nOriginal Title : BB VS HIKAKIN EX 口技对决 Bad Apple\nCreator :  尹浩S\nhttp:\/\/pan.baidu.com\/s\/1hsEYXnu","thumbnails":{"default":{"url":"https:\/\/i.ytimg.com\/vi\/CQh-NgB_jzc\/default.jpg","width":120,"height":90},"medium":{"url":"https:\/\/i.ytimg.com\/vi\/CQh-NgB_jzc\/mqdefault.jpg","width":320,"height":180},"high":{"url":"https:\/\/i.ytimg.com\/vi\/CQh-NgB_jzc\/hqdefault.jpg","width":480,"height":360},"standard":{"url":"https:\/\/i.ytimg.com\/vi\/CQh-NgB_jzc\/sddefault.jpg","width":640,"height":480}},"channelTitle":"최환","playlistId":"PLFRP2_rfZcgDYy9PXVgKrxdFhEW4OnYXa","position":14,"resourceId":{"kind":"youtube#video","videoId":"CQh-NgB_jzc"},"videoOwnerChannelTitle":"[オルタ]えありい","videoOwnerChannelId":"UCMn6norCjpBXb-aJmAR1bNg"}},{"kind":"youtube#playlistItem","etag":"hCtdrg9rqz7IYrs3DDxiTsgmJ84","id":"UExGUlAyX3JmWmNnRFl5OVBYVmdLcnhkRmhFVzRPbllYYS41MzY4MzcwOUFFRUU3QzEx","snippet":{"publishedAt":"2016-08-08T12:11:04Z","channelId":"UCZ2I0UZvP3cEcbgESWxkHmA","title":"Deleted video","description":"This video is unavailable.","thumbnails":{},"channelTitle":"최환","playlistId":"PLFRP2_rfZcgDYy9PXVgKrxdFhEW4OnYXa","position":15,"resourceId":{"kind":"youtube#video","videoId":"axs1YGeGdHU"}}},{"kind":"youtube#playlistItem","etag":"b-ZqQhi3IDMLGad4sqizD034EoA","id":"UExGUlAyX3JmWmNnRFl5OVBYVmdLcnhkRmhFVzRPbllYYS4yQjZFRkExQjFGODk3RUFD","snippet":{"publishedAt":"2016-08-08T12:11:10Z","channelId":"UCZ2I0UZvP3cEcbgESWxkHmA","title":"ヒカキン　vsアンナBB","description":"作ってみたb","thumbnails":{"default":{"url":"https:\/\/i.ytimg.com\/vi\/DlN8rqCxmkk\/default.jpg","width":120,"height":90},"medium":{"url":"https:\/\/i.ytimg.com\/vi\/DlN8rqCxmkk\/mqdefault.jpg","width":320,"height":180},"high":{"url":"https:\/\/i.ytimg.com\/vi\/DlN8rqCxmkk\/hqdefault.jpg","width":480,"height":360},"standard":{"url":"https:\/\/i.ytimg.com\/vi\/DlN8rqCxmkk\/sddefault.jpg","width":640,"height":480},"maxres":{"url":"https:\/\/i.ytimg.com\/vi\/DlN8rqCxmkk\/maxresdefault.jpg","width":1280,"height":720}},"channelTitle":"최환","playlistId":"PLFRP2_rfZcgDYy9PXVgKrxdFhEW4OnYXa","position":16,"resourceId":{"kind":"youtube#video","videoId":"DlN8rqCxmkk"},"videoOwnerChannelTitle":"CH STEVE","videoOwnerChannelId":"UCbxq9dxzxSmxtj9F4BW5bAg"}},{"kind":"youtube#playlistItem","etag":"Nd5-EoZnQOTPFWJCcpfOKJ9tREo","id":"UExGUlAyX3JmWmNnRFl5OVBYVmdLcnhkRmhFVzRPbllYYS4yQUJFNUVCMzVDNjcxRTlF","snippet":{"publishedAt":"2016-08-08T12:11:27Z","channelId":"UCZ2I0UZvP3cEcbgESWxkHmA","title":"TEST Another","description":"これ2回目やね","thumbnails":{"default":{"url":"https:\/\/i.ytimg.com\/vi\/QDxV823ExW4\/default.jpg","width":120,"height":90},"medium":{"url":"https:\/\/i.ytimg.com\/vi\/QDxV823ExW4\/mqdefault.jpg","width":320,"height":180},"high":{"url":"https:\/\/i.ytimg.com\/vi\/QDxV823ExW4\/hqdefault.jpg","width":480,"height":360},"standard":{"url":"https:\/\/i.ytimg.com\/vi\/QDxV823ExW4\/sddefault.jpg","width":640,"height":480},"maxres":{"url":"https:\/\/i.ytimg.com\/vi\/QDxV823ExW4\/maxresdefault.jpg","width":1280,"height":720}},"channelTitle":"최환","playlistId":"PLFRP2_rfZcgDYy9PXVgKrxdFhEW4OnYXa","position":17,"resourceId":{"kind":"youtube#video","videoId":"QDxV823ExW4"},"videoOwnerChannelTitle":"CH STEVE","videoOwnerChannelId":"UCbxq9dxzxSmxtj9F4BW5bAg"}},{"kind":"youtube#playlistItem","etag":"7OzF2J5U9wLC3Wt9hy1zV-JNNtU","id":"UExGUlAyX3JmWmNnRFl5OVBYVmdLcnhkRmhFVzRPbllYYS40QzRDOEU0QUYwNUIxN0M1","snippet":{"publishedAt":"2016-08-08T12:13:02Z","channelId":"UCZ2I0UZvP3cEcbgESWxkHmA","title":"BlueBack vs HIKAKIN Voice Percussion Battle BadApple!!","description":"致命的な編集ミスがあったので音速で再うｐしましたｗ","thumbnails":{"default":{"url":"https:\/\/i.ytimg.com\/vi\/SsG25r2zZ3E\/default.jpg","width":120,"height":90},"medium":{"url":"https:\/\/i.ytimg.com\/vi\/SsG25r2zZ3E\/mqdefault.jpg","width":320,"height":180},"high":{"url":"https:\/\/i.ytimg.com\/vi\/SsG25r2zZ3E\/hqdefault.jpg","width":480,"height":360},"standard":{"url":"https:\/\/i.ytimg.com\/vi\/SsG25r2zZ3E\/sddefault.jpg","width":640,"height":480},"maxres":{"url":"https:\/\/i.ytimg.com\/vi\/SsG25r2zZ3E\/maxresdefault.jpg","width":1280,"height":720}},"channelTitle":"최환","playlistId":"PLFRP2_rfZcgDYy9PXVgKrxdFhEW4OnYXa","position":18,"resourceId":{"kind":"youtube#video","videoId":"SsG25r2zZ3E"},"videoOwnerChannelTitle":"CH STEVE","videoOwnerChannelId":"UCbxq9dxzxSmxtj9F4BW5bAg"}},{"kind":"youtube#playlistItem","etag":"gP_mFQHh1VVOyHc4wlTLTzKQAqQ","id":"UExGUlAyX3JmWmNnRFl5OVBYVmdLcnhkRmhFVzRPbllYYS41RTNBREYwMkI5QzU3RkY2","snippet":{"publishedAt":"2016-08-08T12:13:09Z","channelId":"UCZ2I0UZvP3cEcbgESWxkHmA","title":"Overlord H   修正版","description":"Murioka氏から指摘があったので音声を修正しました","thumbnails":{"default":{"url":"https:\/\/i.ytimg.com\/vi\/fiRbXngc86Q\/default.jpg","width":120,"height":90},"medium":{"url":"https:\/\/i.ytimg.com\/vi\/fiRbXngc86Q\/mqdefault.jpg","width":320,"height":180},"high":{"url":"https:\/\/i.ytimg.com\/vi\/fiRbXngc86Q\/hqdefault.jpg","width":480,"height":360},"standard":{"url":"https:\/\/i.ytimg.com\/vi\/fiRbXngc86Q\/sddefault.jpg","width":640,"height":480},"maxres":{"url":"https:\/\/i.ytimg.com\/vi\/fiRbXngc86Q\/maxresdefault.jpg","width":1280,"height":720}},"channelTitle":"최환","playlistId":"PLFRP2_rfZcgDYy9PXVgKrxdFhEW4OnYXa","position":19,"resourceId":{"kind":"youtube#video","videoId":"fiRbXngc86Q"},"videoOwnerChannelTitle":"CH STEVE","videoOwnerChannelId":"UCbxq9dxzxSmxtj9F4BW5bAg"}},{"kind":"youtube#playlistItem","etag":"7uAAvb0MEvZ7STbyf7fjTweuBc8","id":"UExGUlAyX3JmWmNnRFl5OVBYVmdLcnhkRmhFVzRPbllYYS44QzVGQUU2QjE2NDgxM0M4","snippet":{"publishedAt":"2016-08-08T12:15:29Z","channelId":"UCZ2I0UZvP3cEcbgESWxkHmA","title":"BB VS OVERLORD H ボイパ対決 8Bit Apple!! (v2)","description":"Inspired by: http:\/\/www.youtube.com\/watch?v=YEic6t0-550 (I still think this one sounds a little better)\nBGM: http:\/\/www.youtube.com\/watch?v=v9h7s0gE05I\nFont Used: Press Start 2P","thumbnails":{"default":{"url":"https:\/\/i.ytimg.com\/vi\/tEnFAVk9P4s\/default.jpg","width":120,"height":90},"medium":{"url":"https:\/\/i.ytimg.com\/vi\/tEnFAVk9P4s\/mqdefault.jpg","width":320,"height":180},"high":{"url":"https:\/\/i.ytimg.com\/vi\/tEnFAVk9P4s\/hqdefault.jpg","width":480,"height":360},"standard":{"url":"https:\/\/i.ytimg.com\/vi\/tEnFAVk9P4s\/sddefault.jpg","width":640,"height":480},"maxres":{"url":"https:\/\/i.ytimg.com\/vi\/tEnFAVk9P4s\/maxresdefault.jpg","width":1280,"height":720}},"channelTitle":"최환","playlistId":"PLFRP2_rfZcgDYy9PXVgKrxdFhEW4OnYXa","position":20,"resourceId":{"kind":"youtube#video","videoId":"tEnFAVk9P4s"},"videoOwnerChannelTitle":"ＤＡＭＯ.","videoOwnerChannelId":"UC4Fd73MocrFcljE0IzfMVXg"}},{"kind":"youtube#playlistItem","etag":"lyEcUFsh46mYuZhMFE8adMOTVYw","id":"UExGUlAyX3JmWmNnRFl5OVBYVmdLcnhkRmhFVzRPbllYYS4xMzgwMzBERjQ4NjEzNUE5","snippet":{"publishedAt":"2016-08-08T12:15:33Z","channelId":"UCZ2I0UZvP3cEcbgESWxkHmA","title":"Private video","description":"This video is private.","thumbnails":{},"channelTitle":"최환","playlistId":"PLFRP2_rfZcgDYy9PXVgKrxdFhEW4OnYXa","position":21,"resourceId":{"kind":"youtube#video","videoId":"GjLlvQhUihQ"}}},{"kind":"youtube#playlistItem","etag":"KHWkHvY_sh8vKQtudP60KcjcRS4","id":"UExGUlAyX3JmWmNnRFl5OVBYVmdLcnhkRmhFVzRPbllYYS4zMEQ1MEIyRTFGNzhDQzFB","snippet":{"publishedAt":"2016-08-08T12:15:45Z","channelId":"UCZ2I0UZvP3cEcbgESWxkHmA","title":"Private video","description":"This video is private.","thumbnails":{},"channelTitle":"최환","playlistId":"PLFRP2_rfZcgDYy9PXVgKrxdFhEW4OnYXa","position":22,"resourceId":{"kind":"youtube#video","videoId":"NITybdlXgs0"}}},{"kind":"youtube#playlistItem","etag":"m5iRjgboCLDgtgbjwP9p4aOx0cY","id":"UExGUlAyX3JmWmNnRFl5OVBYVmdLcnhkRmhFVzRPbllYYS42Qzk5MkEzQjVFQjYwRDA4","snippet":{"publishedAt":"2016-08-08T12:15:47Z","channelId":"UCZ2I0UZvP3cEcbgESWxkHmA","title":"Private video","description":"This video is private.","thumbnails":{},"channelTitle":"최환","playlistId":"PLFRP2_rfZcgDYy9PXVgKrxdFhEW4OnYXa","position":23,"resourceId":{"kind":"youtube#video","videoId":"c2EfH3ZxBrk"}}},{"kind":"youtube#playlistItem","etag":"8Y1WCwqESgNwX8Zpx9WCXb2WjGU","id":"UExGUlAyX3JmWmNnRFl5OVBYVmdLcnhkRmhFVzRPbllYYS41NTZEOThBNThFOUVGQkVB","snippet":{"publishedAt":"2016-08-08T12:16:54Z","channelId":"UCZ2I0UZvP3cEcbgESWxkHmA","title":"【素材】BB VS ヒカキン ボイパ対决 Little Devil's Apple!!","description":"リクエストはコメで","thumbnails":{"default":{"url":"https:\/\/i.ytimg.com\/vi\/l7_x9CtGWqw\/default.jpg","width":120,"height":90},"medium":{"url":"https:\/\/i.ytimg.com\/vi\/l7_x9CtGWqw\/mqdefault.jpg","width":320,"height":180},"high":{"url":"https:\/\/i.ytimg.com\/vi\/l7_x9CtGWqw\/hqdefault.jpg","width":480,"height":360},"standard":{"url":"https:\/\/i.ytimg.com\/vi\/l7_x9CtGWqw\/sddefault.jpg","width":640,"height":480},"maxres":{"url":"https:\/\/i.ytimg.com\/vi\/l7_x9CtGWqw\/maxresdefault.jpg","width":1280,"height":720}},"channelTitle":"최환","playlistId":"PLFRP2_rfZcgDYy9PXVgKrxdFhEW4OnYXa","position":24,"resourceId":{"kind":"youtube#video","videoId":"l7_x9CtGWqw"},"videoOwnerChannelTitle":"佐世保","videoOwnerChannelId":"UCocnqSKOHuopVyCP72bqGwA"}},{"kind":"youtube#playlistItem","etag":"7_qON4vkuQd47LC80TcUuhxVdRs","id":"UExGUlAyX3JmWmNnRFl5OVBYVmdLcnhkRmhFVzRPbllYYS43NERCMDIzQzFBMERCMEE3","snippet":{"publishedAt":"2016-08-13T03:41:23Z","channelId":"UCZ2I0UZvP3cEcbgESWxkHmA","title":"YB vs HIKAKIN ボイパ対決(素材) bad apple!!","description":"お借りした素材\nhttps:\/\/www.youtube.com\/watch?v=BwSPnDqdWtw\n走査線あり 後日投稿","thumbnails":{"default":{"url":"https:\/\/i.ytimg.com\/vi\/83bTVC5IG9c\/default.jpg","width":120,"height":90},"medium":{"url":"https:\/\/i.ytimg.com\/vi\/83bTVC5IG9c\/mqdefault.jpg","width":320,"height":180},"high":{"url":"https:\/\/i.ytimg.com\/vi\/83bTVC5IG9c\/hqdefault.jpg","width":480,"height":360},"standard":{"url":"https:\/\/i.ytimg.com\/vi\/83bTVC5IG9c\/sddefault.jpg","width":640,"height":480}},"channelTitle":"최환","playlistId":"PLFRP2_rfZcgDYy9PXVgKrxdFhEW4OnYXa","position":25,"resourceId":{"kind":"youtube#video","videoId":"83bTVC5IG9c"},"videoOwnerChannelTitle":"いなり","videoOwnerChannelId":"UCRK4Y0cDSnwHFLX_VHwgrQw"}},{"kind":"youtube#playlistItem","etag":"E2SHPg4ZcMESe3zqtvIXehpLuiM","id":"UExGUlAyX3JmWmNnRFl5OVBYVmdLcnhkRmhFVzRPbllYYS4wNEU1MTI4NkZEMzVBN0JF","snippet":{"publishedAt":"2016-08-16T06:29:39Z","channelId":"UCZ2I0UZvP3cEcbgESWxkHmA","title":"Mutant H　GB素材","description":"!","thumbnails":{"default":{"url":"https:\/\/i.ytimg.com\/vi\/beS1-i0e-VY\/default.jpg","width":120,"height":90},"medium":{"url":"https:\/\/i.ytimg.com\/vi\/beS1-i0e-VY\/mqdefault.jpg","width":320,"height":180},"high":{"url":"https:\/\/i.ytimg.com\/vi\/beS1-i0e-VY\/hqdefault.jpg","width":480,"height":360},"standard":{"url":"https:\/\/i.ytimg.com\/vi\/beS1-i0e-VY\/sddefault.jpg","width":640,"height":480},"maxres":{"url":"https:\/\/i.ytimg.com\/vi\/beS1-i0e-VY\/maxresdefault.jpg","width":1280,"height":720}},"channelTitle":"최환","playlistId":"PLFRP2_rfZcgDYy9PXVgKrxdFhEW4OnYXa","position":26,"resourceId":{"kind":"youtube#video","videoId":"beS1-i0e-VY"},"videoOwnerChannelTitle":"Mel","videoOwnerChannelId":"UCSXP6UV3O8JvG7LsfhU1dlQ"}},{"kind":"youtube#playlistItem","etag":"2MuyaNfq5RrPhwrPsdZq27B7ZQQ","id":"UExGUlAyX3JmWmNnRFl5OVBYVmdLcnhkRmhFVzRPbllYYS4wMTYxQzVBRDI1NEVDQUZE","snippet":{"publishedAt":"2016-08-16T06:29:44Z","channelId":"UCZ2I0UZvP3cEcbgESWxkHmA","title":"Deleted video","description":"This video is unavailable.","thumbnails":{},"channelTitle":"최환","playlistId":"PLFRP2_rfZcgDYy9PXVgKrxdFhEW4OnYXa","position":27,"resourceId":{"kind":"youtube#video","videoId":"oTsr8F0PQo8"}}},{"kind":"youtube#playlistItem","etag":"cfzUwsLe7ViT4tu90m787105w3k","id":"UExGUlAyX3JmWmNnRFl5OVBYVmdLcnhkRmhFVzRPbllYYS4zMUEyMkQwOTk0NTg4MDgw","snippet":{"publishedAt":"2016-08-16T06:29:56Z","channelId":"UCZ2I0UZvP3cEcbgESWxkHmA","title":"Deleted video","description":"This video is unavailable.","thumbnails":{},"channelTitle":"최환","playlistId":"PLFRP2_rfZcgDYy9PXVgKrxdFhEW4OnYXa","position":28,"resourceId":{"kind":"youtube#video","videoId":"SH5UOiHOC8I"}}},{"kind":"youtube#playlistItem","etag":"Csbkdab2xARqf5jVTtT4P6HQsdc","id":"UExGUlAyX3JmWmNnRFl5OVBYVmdLcnhkRmhFVzRPbllYYS41OURENDc2NEM1MDI5Mjky","snippet":{"publishedAt":"2016-08-16T06:30:30Z","channelId":"UCZ2I0UZvP3cEcbgESWxkHmA","title":"Deleted video","description":"This video is unavailable.","thumbnails":{},"channelTitle":"최환","playlistId":"PLFRP2_rfZcgDYy9PXVgKrxdFhEW4OnYXa","position":29,"resourceId":{"kind":"youtube#video","videoId":"kVZ2HfW3OsI"}}},{"kind":"youtube#playlistItem","etag":"Q96zeihQqmrAcKHNgTr9kgjS2tI","id":"UExGUlAyX3JmWmNnRFl5OVBYVmdLcnhkRmhFVzRPbllYYS4wRjhFM0MxMTU1MEUzQ0VB","snippet":{"publishedAt":"2016-08-17T06:46:59Z","channelId":"UCZ2I0UZvP3cEcbgESWxkHmA","title":"Private video","description":"This video is private.","thumbnails":{},"channelTitle":"최환","playlistId":"PLFRP2_rfZcgDYy9PXVgKrxdFhEW4OnYXa","position":30,"resourceId":{"kind":"youtube#video","videoId":"mU4pNm18unc"}}},{"kind":"youtube#playlistItem","etag":"fNcGyOinQPhYyYTojiDU1_VRcy4","id":"UExGUlAyX3JmWmNnRFl5OVBYVmdLcnhkRmhFVzRPbllYYS5CNTZFOTNGQzZEODg1RUQx","snippet":{"publishedAt":"2016-08-17T06:47:08Z","channelId":"UCZ2I0UZvP3cEcbgESWxkHmA","title":"BB VS Overlord H ボイパ対決 Little Devil's Apple","description":"先駆者様:https:\/\/youtu.be\/xoks0bBS3wc (ようかいむら2さん)\n使用映像:https:\/\/youtu.be\/ZK0rYaxhh-Q (Brothers Smashさん)\n使用音声:Overlord H Voice Material(6 Materials)(AEさん)","thumbnails":{"default":{"url":"https:\/\/i.ytimg.com\/vi\/UGmto7nQ6vQ\/default.jpg","width":120,"height":90},"medium":{"url":"https:\/\/i.ytimg.com\/vi\/UGmto7nQ6vQ\/mqdefault.jpg","width":320,"height":180},"high":{"url":"https:\/\/i.ytimg.com\/vi\/UGmto7nQ6vQ\/hqdefault.jpg","width":480,"height":360},"standard":{"url":"https:\/\/i.ytimg.com\/vi\/UGmto7nQ6vQ\/sddefault.jpg","width":640,"height":480},"maxres":{"url":"https:\/\/i.ytimg.com\/vi\/UGmto7nQ6vQ\/maxresdefault.jpg","width":1280,"height":720}},"channelTitle":"최환","playlistId":"PLFRP2_rfZcgDYy9PXVgKrxdFhEW4OnYXa","position":31,"resourceId":{"kind":"youtube#video","videoId":"UGmto7nQ6vQ"},"videoOwnerChannelTitle":"魔琥怒鳴奴","videoOwnerChannelId":"UCInXAc7Xiy2PwDjNELGQGKQ"}},{"kind":"youtube#playlistItem","etag":"lLr_-GOjZ0eWF6X1eJUWc_JqCU4","id":"UExGUlAyX3JmWmNnRFl5OVBYVmdLcnhkRmhFVzRPbllYYS5CNTcxMDQ0NThBNzMxODYz","snippet":{"publishedAt":"2016-08-18T12:47:56Z","channelId":"UCZ2I0UZvP3cEcbgESWxkHmA","title":"Private video","description":"This video is private.","thumbnails":{},"channelTitle":"최환","playlistId":"PLFRP2_rfZcgDYy9PXVgKrxdFhEW4OnYXa","position":32,"resourceId":{"kind":"youtube#video","videoId":"Vt2hI-LnpD0"}}},{"kind":"youtube#playlistItem","etag":"8fkyWcvP34EyZLj-R3m4o0wbr4c","id":"UExGUlAyX3JmWmNnRFl5OVBYVmdLcnhkRmhFVzRPbllYYS42MjYzMTMyQjA0QURCN0JF","snippet":{"publishedAt":"2016-08-30T08:54:02Z","channelId":"UCZ2I0UZvP3cEcbgESWxkHmA","title":"BB vs another H ボイパ対決 Bad Apple!!","description":"ヒカキンにしてはいい戦いだな\nはい、どうもミツオです！初BBを作ってみました！下手ですがご自由にお使いください！借りる際はコメント欄に書いてくれるとありがたいです。\n修正してほしい部分はコメント欄に書いてくれると助かります！","thumbnails":{"default":{"url":"https:\/\/i.ytimg.com\/vi\/5bFTI09bruQ\/default.jpg","width":120,"height":90},"medium":{"url":"https:\/\/i.ytimg.com\/vi\/5bFTI09bruQ\/mqdefault.jpg","width":320,"height":180},"high":{"url":"https:\/\/i.ytimg.com\/vi\/5bFTI09bruQ\/hqdefault.jpg","width":480,"height":360},"standard":{"url":"https:\/\/i.ytimg.com\/vi\/5bFTI09bruQ\/sddefault.jpg","width":640,"height":480},"maxres":{"url":"https:\/\/i.ytimg.com\/vi\/5bFTI09bruQ\/maxresdefault.jpg","width":1280,"height":720}},"channelTitle":"최환","playlistId":"PLFRP2_rfZcgDYy9PXVgKrxdFhEW4OnYXa","position":33,"resourceId":{"kind":"youtube#video","videoId":"5bFTI09bruQ"},"videoOwnerChannelTitle":"ミツオ","videoOwnerChannelId":"UC8v9oAqXhVKZl_4TCEuqzsg"}},{"kind":"youtube#playlistItem","etag":"8n0WDVS8HGg_ioeLwVP3tPWbzVE","id":"UExGUlAyX3JmWmNnRFl5OVBYVmdLcnhkRmhFVzRPbllYYS40MDNEMzA0QTBFRThFMzBE","snippet":{"publishedAt":"2016-08-30T13:45:34Z","channelId":"UCZ2I0UZvP3cEcbgESWxkHmA","title":"Deleted video","description":"This video is unavailable.","thumbnails":{},"channelTitle":"최환","playlistId":"PLFRP2_rfZcgDYy9PXVgKrxdFhEW4OnYXa","position":34,"resourceId":{"kind":"youtube#video","videoId":"OYsMFk0-ofg"}}},{"kind":"youtube#playlistItem","etag":"8kFzdjKVEI5S84EQDHmtmS1z6NU","id":"UExGUlAyX3JmWmNnRFl5OVBYVmdLcnhkRmhFVzRPbllYYS42RTNCOEMxREI3Q0VDMjU2","snippet":{"publishedAt":"2016-08-30T23:21:45Z","channelId":"UCZ2I0UZvP3cEcbgESWxkHmA","title":"BB VS OVERLORD H ボイパ対決 8Bit Apple!! (v2)","description":"Inspired by: http:\/\/www.youtube.com\/watch?v=YEic6t0-550 (I still think this one sounds a little better)\nBGM: http:\/\/www.youtube.com\/watch?v=v9h7s0gE05I\nFont Used: Press Start 2P","thumbnails":{"default":{"url":"https:\/\/i.ytimg.com\/vi\/tEnFAVk9P4s\/default.jpg","width":120,"height":90},"medium":{"url":"https:\/\/i.ytimg.com\/vi\/tEnFAVk9P4s\/mqdefault.jpg","width":320,"height":180},"high":{"url":"https:\/\/i.ytimg.com\/vi\/tEnFAVk9P4s\/hqdefault.jpg","width":480,"height":360},"standard":{"url":"https:\/\/i.ytimg.com\/vi\/tEnFAVk9P4s\/sddefault.jpg","width":640,"height":480},"maxres":{"url":"https:\/\/i.ytimg.com\/vi\/tEnFAVk9P4s\/maxresdefault.jpg","width":1280,"height":720}},"channelTitle":"최환","playlistId":"PLFRP2_rfZcgDYy9PXVgKrxdFhEW4OnYXa","position":35,"resourceId":{"kind":"youtube#video","videoId":"tEnFAVk9P4s"},"videoOwnerChannelTitle":"ＤＡＭＯ.","videoOwnerChannelId":"UC4Fd73MocrFcljE0IzfMVXg"}},{"kind":"youtube#playlistItem","etag":"PulPSVyEbKdzTxzXkUhJQUOwMbw","id":"UExGUlAyX3JmWmNnRFl5OVBYVmdLcnhkRmhFVzRPbllYYS43QzNCNkZENzIyMDY2MjZB","snippet":{"publishedAt":"2016-08-30T23:22:51Z","channelId":"UCZ2I0UZvP3cEcbgESWxkHmA","title":"【再うp】BB VS sm666 ボイパ対決 Bad Apple!!","description":"","thumbnails":{"default":{"url":"https:\/\/i.ytimg.com\/vi\/cb0J-rZiLbc\/default.jpg","width":120,"height":90},"medium":{"url":"https:\/\/i.ytimg.com\/vi\/cb0J-rZiLbc\/mqdefault.jpg","width":320,"height":180},"high":{"url":"https:\/\/i.ytimg.com\/vi\/cb0J-rZiLbc\/hqdefault.jpg","width":480,"height":360},"standard":{"url":"https:\/\/i.ytimg.com\/vi\/cb0J-rZiLbc\/sddefault.jpg","width":640,"height":480},"maxres":{"url":"https:\/\/i.ytimg.com\/vi\/cb0J-rZiLbc\/maxresdefault.jpg","width":1280,"height":720}},"channelTitle":"최환","playlistId":"PLFRP2_rfZcgDYy9PXVgKrxdFhEW4OnYXa","position":36,"resourceId":{"kind":"youtube#video","videoId":"cb0J-rZiLbc"},"videoOwnerChannelTitle":"ぽうかいむら","videoOwnerChannelId":"UCx9EEAdyiN5riC2Q7ptqrpg"}},{"kind":"youtube#playlistItem","etag":"5k8Yy7_Ir4zfv_LKsAfJ04p5vek","id":"UExGUlAyX3JmWmNnRFl5OVBYVmdLcnhkRmhFVzRPbllYYS5EQkE3RTJCQTJEQkFBQTcz","snippet":{"publishedAt":"2016-08-30T23:23:15Z","channelId":"UCZ2I0UZvP3cEcbgESWxkHmA","title":"Mutant H　GB素材","description":"!","thumbnails":{"default":{"url":"https:\/\/i.ytimg.com\/vi\/beS1-i0e-VY\/default.jpg","width":120,"height":90},"medium":{"url":"https:\/\/i.ytimg.com\/vi\/beS1-i0e-VY\/mqdefault.jpg","width":320,"height":180},"high":{"url":"https:\/\/i.ytimg.com\/vi\/beS1-i0e-VY\/hqdefault.jpg","width":480,"height":360},"standard":{"url":"https:\/\/i.ytimg.com\/vi\/beS1-i0e-VY\/sddefault.jpg","width":640,"height":480},"maxres":{"url":"https:\/\/i.ytimg.com\/vi\/beS1-i0e-VY\/maxresdefault.jpg","width":1280,"height":720}},"channelTitle":"최환","playlistId":"PLFRP2_rfZcgDYy9PXVgKrxdFhEW4OnYXa","position":37,"resourceId":{"kind":"youtube#video","videoId":"beS1-i0e-VY"},"videoOwnerChannelTitle":"Mel","videoOwnerChannelId":"UCSXP6UV3O8JvG7LsfhU1dlQ"}},{"kind":"youtube#playlistItem","etag":"Bg0ljAH9ATm0MNAPXZ6ZcryhZbI","id":"UExGUlAyX3JmWmNnRFl5OVBYVmdLcnhkRmhFVzRPbllYYS4yQzk4QTA5QjkzMTFFOEI1","snippet":{"publishedAt":"2016-08-30T23:24:00Z","channelId":"UCZ2I0UZvP3cEcbgESWxkHmA","title":"Private video","description":"This video is private.","thumbnails":{},"channelTitle":"최환","playlistId":"PLFRP2_rfZcgDYy9PXVgKrxdFhEW4OnYXa","position":38,"resourceId":{"kind":"youtube#video","videoId":"8FtBwshRQn0"}}},{"kind":"youtube#playlistItem","etag":"W2pN3uvlkLLEdeMQtXKCoJbEGWU","id":"UExGUlAyX3JmWmNnRFl5OVBYVmdLcnhkRmhFVzRPbllYYS45NDlDQUFFOThDMTAxQjUw","snippet":{"publishedAt":"2016-08-30T23:24:09Z","channelId":"UCZ2I0UZvP3cEcbgESWxkHmA","title":"Private video","description":"This video is private.","thumbnails":{},"channelTitle":"최환","playlistId":"PLFRP2_rfZcgDYy9PXVgKrxdFhEW4OnYXa","position":39,"resourceId":{"kind":"youtube#video","videoId":"MHlFWBzrqqM"}}},{"kind":"youtube#playlistItem","etag":"NCNQpcPXk2Qze1I1oRfgoqAg1xs","id":"UExGUlAyX3JmWmNnRFl5OVBYVmdLcnhkRmhFVzRPbllYYS5FQUY2Qzk4RUFDN0ZFRkZF","snippet":{"publishedAt":"2016-08-30T23:25:08Z","channelId":"UCZ2I0UZvP3cEcbgESWxkHmA","title":"Private video","description":"This video is private.","thumbnails":{},"channelTitle":"최환","playlistId":"PLFRP2_rfZcgDYy9PXVgKrxdFhEW4OnYXa","position":40,"resourceId":{"kind":"youtube#video","videoId":"FqLkYGH4tW0"}}},{"kind":"youtube#playlistItem","etag":"CLNpiLeSxDaCPR7LrdCK5MsAMlQ","id":"UExGUlAyX3JmWmNnRFl5OVBYVmdLcnhkRmhFVzRPbllYYS4xNjIyNEE0MDEyRDlCMjBE","snippet":{"publishedAt":"2016-08-30T23:25:42Z","channelId":"UCZ2I0UZvP3cEcbgESWxkHmA","title":"Private video","description":"This video is private.","thumbnails":{},"channelTitle":"최환","playlistId":"PLFRP2_rfZcgDYy9PXVgKrxdFhEW4OnYXa","position":41,"resourceId":{"kind":"youtube#video","videoId":"gx7l5NWjWhU"}}},{"kind":"youtube#playlistItem","etag":"47QkbmLXRH2fqfs36A3LlpXAmrc","id":"UExGUlAyX3JmWmNnRFl5OVBYVmdLcnhkRmhFVzRPbllYYS4zQTkzRjgxRTY0OEU0MkM3","snippet":{"publishedAt":"2016-08-30T23:26:19Z","channelId":"UCZ2I0UZvP3cEcbgESWxkHmA","title":"BB vs another H ボイパ対決 Bad Apple!!","description":"ヒカキンにしてはいい戦いだな\nはい、どうもミツオです！初BBを作ってみました！下手ですがご自由にお使いください！借りる際はコメント欄に書いてくれるとありがたいです。\n修正してほしい部分はコメント欄に書いてくれると助かります！","thumbnails":{"default":{"url":"https:\/\/i.ytimg.com\/vi\/5bFTI09bruQ\/default.jpg","width":120,"height":90},"medium":{"url":"https:\/\/i.ytimg.com\/vi\/5bFTI09bruQ\/mqdefault.jpg","width":320,"height":180},"high":{"url":"https:\/\/i.ytimg.com\/vi\/5bFTI09bruQ\/hqdefault.jpg","width":480,"height":360},"standard":{"url":"https:\/\/i.ytimg.com\/vi\/5bFTI09bruQ\/sddefault.jpg","width":640,"height":480},"maxres":{"url":"https:\/\/i.ytimg.com\/vi\/5bFTI09bruQ\/maxresdefault.jpg","width":1280,"height":720}},"channelTitle":"최환","playlistId":"PLFRP2_rfZcgDYy9PXVgKrxdFhEW4OnYXa","position":42,"resourceId":{"kind":"youtube#video","videoId":"5bFTI09bruQ"},"videoOwnerChannelTitle":"ミツオ","videoOwnerChannelId":"UC8v9oAqXhVKZl_4TCEuqzsg"}},{"kind":"youtube#playlistItem","etag":"bVkA9GGcYL6okl_iw2SWsYEDMes","id":"UExGUlAyX3JmWmNnRFl5OVBYVmdLcnhkRmhFVzRPbllYYS4xNTZBNUQxMDZBQzFGMjkw","snippet":{"publishedAt":"2016-09-01T06:38:07Z","channelId":"UCZ2I0UZvP3cEcbgESWxkHmA","title":"Private video","description":"This video is private.","thumbnails":{},"channelTitle":"최환","playlistId":"PLFRP2_rfZcgDYy9PXVgKrxdFhEW4OnYXa","position":43,"resourceId":{"kind":"youtube#video","videoId":"_pfjcJl_GqQ"}}},{"kind":"youtube#playlistItem","etag":"ebv19MD-mXkev_aeh74W5ecpeSc","id":"UExGUlAyX3JmWmNnRFl5OVBYVmdLcnhkRmhFVzRPbllYYS4wMDFGNzBEOTU4Q0Y1Q0RG","snippet":{"publishedAt":"2016-09-01T06:38:16Z","channelId":"UCZ2I0UZvP3cEcbgESWxkHmA","title":"Private video","description":"This video is private.","thumbnails":{},"channelTitle":"최환","playlistId":"PLFRP2_rfZcgDYy9PXVgKrxdFhEW4OnYXa","position":44,"resourceId":{"kind":"youtube#video","videoId":"c2EfH3ZxBrk"}}},{"kind":"youtube#playlistItem","etag":"7hz-zvdoexGUgwe6XYPadklLvtI","id":"UExGUlAyX3JmWmNnRFl5OVBYVmdLcnhkRmhFVzRPbllYYS44QTA1QTQyRTc3M0VGQzYx","snippet":{"publishedAt":"2016-09-01T06:43:42Z","channelId":"UCZ2I0UZvP3cEcbgESWxkHmA","title":"Private video","description":"This video is private.","thumbnails":{},"channelTitle":"최환","playlistId":"PLFRP2_rfZcgDYy9PXVgKrxdFhEW4OnYXa","position":45,"resourceId":{"kind":"youtube#video","videoId":"pfiXDgT4NKc"}}},{"kind":"youtube#playlistItem","etag":"Fo00F4eCcZt0AjfM64hL3GueFM0","id":"UExGUlAyX3JmWmNnRFl5OVBYVmdLcnhkRmhFVzRPbllYYS40NzE2MTY1QTM3RUI3QkU3","snippet":{"publishedAt":"2016-09-05T14:46:40Z","channelId":"UCZ2I0UZvP3cEcbgESWxkHmA","title":"Private video","description":"This video is private.","thumbnails":{},"channelTitle":"최환","playlistId":"PLFRP2_rfZcgDYy9PXVgKrxdFhEW4OnYXa","position":46,"resourceId":{"kind":"youtube#video","videoId":"MHlFWBzrqqM"}}},{"kind":"youtube#playlistItem","etag":"gL3lhmcWj3JO_Y1M6UgG9kE7sao","id":"UExGUlAyX3JmWmNnRFl5OVBYVmdLcnhkRmhFVzRPbllYYS5EMzJDRTUwQjBEOUVFQzAw","snippet":{"publishedAt":"2016-09-05T14:47:04Z","channelId":"UCZ2I0UZvP3cEcbgESWxkHmA","title":"Private video","description":"This video is private.","thumbnails":{},"channelTitle":"최환","playlistId":"PLFRP2_rfZcgDYy9PXVgKrxdFhEW4OnYXa","position":47,"resourceId":{"kind":"youtube#video","videoId":"5wJAQLwVaPs"}}},{"kind":"youtube#playlistItem","etag":"LJbASgPlMMl4KuvXXj5XLqV-BnA","id":"UExGUlAyX3JmWmNnRFl5OVBYVmdLcnhkRmhFVzRPbllYYS5CMUM0NzY5NzdEQzlGRjAx","snippet":{"publishedAt":"2016-09-05T14:48:06Z","channelId":"UCZ2I0UZvP3cEcbgESWxkHmA","title":"Deleted video","description":"This video is unavailable.","thumbnails":{},"channelTitle":"최환","playlistId":"PLFRP2_rfZcgDYy9PXVgKrxdFhEW4OnYXa","position":48,"resourceId":{"kind":"youtube#video","videoId":"u6_uNH5-a_I"}}},{"kind":"youtube#playlistItem","etag":"RFXmRIbyH5184WejWgoa0tHEWk4","id":"UExGUlAyX3JmWmNnRFl5OVBYVmdLcnhkRmhFVzRPbllYYS5DQjg2RDQyMEVGQkZFOEVF","snippet":{"publishedAt":"2016-09-05T14:50:12Z","channelId":"UCZ2I0UZvP3cEcbgESWxkHmA","title":"Private video","description":"This video is private.","thumbnails":{},"channelTitle":"최환","playlistId":"PLFRP2_rfZcgDYy9PXVgKrxdFhEW4OnYXa","position":49,"resourceId":{"kind":"youtube#video","videoId":"lyLRQmaDTbo"}}}],"pageInfo":{"totalResults":364,"resultsPerPage":50}}